nbdev/__init__.py
nbdev/_modidx.py
nbdev/clean.py
nbdev/cli.py
nbdev/config.py
nbdev/doclinks.py
nbdev/export.py
nbdev/extract_attachments.py
nbdev/frontmatter.py
nbdev/imports.py
nbdev/maker.py
nbdev/merge.py
nbdev/migrate.py
nbdev/process.py
nbdev/processors.py
nbdev/qmd.py
nbdev/quarto.py
nbdev/release.py
nbdev/serve.py
nbdev/serve_drv.py
nbdev/showdoc.py
nbdev/sync.py
nbdev/test.py
nbdev_simonkeys-2.4.dist-info/LICENSE
nbdev_simonkeys-2.4.dist-info/METADATA
nbdev_simonkeys-2.4.dist-info/WHEEL
nbdev_simonkeys-2.4.dist-info/entry_points.txt
nbdev_simonkeys-2.4.dist-info/top_level.txt
nbdev_simonkeys-2.4.dist-info/RECORD
