Metadata-Version: 2.1
Name: nbdev-simonkeys
Version: 2.4
Summary: Create delightful software with Jupyter Notebooks
Home-page: https://github.com/fastai/nbdev
Author: Jeremy Howard and Hamel Husain
Author-email: j@fast.ai
License: Apache Software License 2.0
Project-URL: Documentation, https://nbdev.fast.ai/
Keywords: nbdev fastai jupyter notebook export
Classifier: Development Status :: 5 - Production/Stable
Classifier: Intended Audience :: Developers
Classifier: Natural Language :: English
Classifier: Programming Language :: Python :: 3.7
Classifier: Programming Language :: Python :: 3.8
Classifier: Programming Language :: Python :: 3.9
Classifier: Programming Language :: Python :: 3.10
Classifier: Programming Language :: Python :: 3.12
Classifier: Programming Language :: Python :: 3.13
Classifier: License :: OSI Approved :: Apache Software License
Requires-Python: >=3.7
License-File: LICENSE
Requires-Dist: packaging
Requires-Dist: fastcore>=1.5.27
Requires-Dist: execnb>=0.1.4
Requires-Dist: astunparse
Requires-Dist: ghapi>=1.0.3
Requires-Dist: watchdog
Requires-Dist: asttokens
Requires-Dist: PyYAML
Provides-Extra: dev
Requires-Dist: ipywidgets; extra == "dev"
Requires-Dist: nbdev-numpy; extra == "dev"
Requires-Dist: nbdev-stdlib; extra == "dev"
Requires-Dist: pandas; extra == "dev"
Requires-Dist: matplotlib; extra == "dev"
Requires-Dist: black; extra == "dev"
Requires-Dist: svg.py; extra == "dev"
Requires-Dist: nbclassic; extra == "dev"
